imed-0.3.0.dist-info/METADATA
imed-0.3.0.dist-info/WHEEL
imed-0.3.0.dist-info/entry_points.txt
imed-0.3.0.dist-info/licenses/LICENSE
imed/__init__.py
imed/frequency.py
imed/imed.py
imed/legacy.py
imed-0.3.0.dist-info/RECORD
