Metadata-Version: 2.1
Name: imed
Version: 0.3.0
Summary: Image Euclidean Distance and Standardizing Transforms
Author-Email: Jacob Ungar Felding <jfelding@gmail.com>, Jacob Felding <jfelding@gmail.com>
License: MIT
Classifier: License :: OSI Approved :: MIT License
Classifier: Operating System :: OS Independent
Classifier: Programming Language :: Python :: 3
Classifier: Programming Language :: Python :: 3.8
Classifier: Programming Language :: Python :: 3.9
Classifier: Programming Language :: Python :: 3.10
Classifier: Programming Language :: Python :: 3.11
Classifier: Programming Language :: Python :: 3.12
Project-URL: Homepage, https://github.com/jfelding/imed
Project-URL: Bug Tracker, https://github.com/jfelding/imed/issues
Requires-Python: >=3.10
Requires-Dist: numpy>=2.2.6
Requires-Dist: scipy>=1.15.3
